{
  "ExtendedData": {
    "inputs": [
      "http://localhost:5007/CookieService/BasicHttp"
    ],
    "collectionTypes": [
      "System.Array",
      "System.Collections.Generic.Dictionary`2"
    ],
    "namespaceMappings": [
      "*, Wcf"
    ],
    "references": [
      "Google.Protobuf, {Google.Protobuf, 3.33.1}",
      "Grpc.Core.Api, {Grpc.Core.Api, 2.71.0}",
      "Grpc.Net.Client, {Grpc.Net.Client, 2.71.0}",
      "Grpc.Net.Common, {Grpc.Net.Common, 2.71.0}",
      "H:\\Repos\\BlazorServer\\src\\BlazorServer.Infrastructure\\bin\\Debug\\net10.0\\BlazorServer.Core.dll",
      "H:\\Repos\\BlazorServer\\src\\BlazorServer.Infrastructure\\bin\\Debug\\net10.0\\BlazorServer.SharedKernel.dll",
      "Microsoft.Data.Sqlite, {Microsoft.Data.Sqlite.Core, 10.0.0}",
      "Microsoft.EntityFrameworkCore, {Microsoft.EntityFrameworkCore, 10.0.0}",
      "Microsoft.EntityFrameworkCore.Abstractions, {Microsoft.EntityFrameworkCore.Abstractions, 10.0.0}",
      "Microsoft.EntityFrameworkCore.Relational, {Microsoft.EntityFrameworkCore.Relational, 10.0.0}",
      "Microsoft.EntityFrameworkCore.Sqlite, {Microsoft.EntityFrameworkCore.Sqlite.Core, 10.0.0}",
      "Microsoft.Extensions.Caching.Abstractions, {Microsoft.Extensions.Caching.Abstractions, 10.0.0}",
      "Microsoft.Extensions.Caching.Memory, {Microsoft.Extensions.Caching.Memory, 10.0.0}",
      "Microsoft.Extensions.Configuration.Abstractions, {Microsoft.Extensions.Configuration.Abstractions, 10.0.0}",
      "Microsoft.Extensions.DependencyInjection, {Microsoft.Extensions.DependencyInjection, 10.0.0}",
      "Microsoft.Extensions.DependencyInjection.Abstractions, {Microsoft.Extensions.DependencyInjection.Abstractions, 10.0.0}",
      "Microsoft.Extensions.DependencyModel, {Microsoft.Extensions.DependencyModel, 10.0.0}",
      "Microsoft.Extensions.Logging, {Microsoft.Extensions.Logging, 10.0.0}",
      "Microsoft.Extensions.Logging.Abstractions, {Microsoft.Extensions.Logging.Abstractions, 10.0.0}",
      "Microsoft.Extensions.ObjectPool, {Microsoft.Extensions.ObjectPool, 10.0.0}",
      "Microsoft.Extensions.Options, {Microsoft.Extensions.Options, 10.0.0}",
      "Microsoft.Extensions.Primitives, {Microsoft.Extensions.Primitives, 10.0.0}",
      "Microsoft.IdentityModel.Abstractions, {Microsoft.IdentityModel.Abstractions, 8.14.0}",
      "Microsoft.IdentityModel.Logging, {Microsoft.IdentityModel.Logging, 8.14.0}",
      "Microsoft.IdentityModel.Protocols.WsTrust, {Microsoft.IdentityModel.Protocols.WsTrust, 6.8.0}",
      "Microsoft.IdentityModel.Tokens, {Microsoft.IdentityModel.Tokens, 8.14.0}",
      "Microsoft.IdentityModel.Tokens.Saml, {Microsoft.IdentityModel.Tokens.Saml, 8.14.0}",
      "Microsoft.IdentityModel.Xml, {Microsoft.IdentityModel.Xml, 8.14.0}",
      "SQLitePCLRaw.batteries_v2, {SQLitePCLRaw.bundle_e_sqlite3, 2.1.11}",
      "SQLitePCLRaw.core, {SQLitePCLRaw.core, 2.1.11}",
      "SQLitePCLRaw.provider.e_sqlite3, {SQLitePCLRaw.provider.e_sqlite3, 2.1.11}",
      "System.Security.Cryptography.Pkcs, {System.Security.Cryptography.Pkcs, 10.0.0}",
      "System.Security.Cryptography.Xml, {System.Security.Cryptography.Xml, 10.0.0}",
      "System.ServiceModel, {System.ServiceModel.Primitives, 10.0.652802}",
      "System.ServiceModel.Duplex, {System.ServiceModel.Duplex, 6.0.0}",
      "System.ServiceModel.Federation, {System.ServiceModel.Federation, 10.0.652802}",
      "System.ServiceModel.Http, {System.ServiceModel.Http, 10.0.652802}",
      "System.ServiceModel.NetFramingBase, {System.ServiceModel.NetFramingBase, 10.0.652802}",
      "System.ServiceModel.NetTcp, {System.ServiceModel.NetTcp, 10.0.652802}",
      "System.ServiceModel.Primitives, {System.ServiceModel.Primitives, 10.0.652802}",
      "System.ServiceModel.Security, {System.ServiceModel.Primitives, 10.0.652802}"
    ],
    "targetFramework": "net10.0",
    "typeReuseMode": "All"
  }
}